apitoolkit_flask/__init__.py
apitoolkit_flask-1.0.3.dist-info/METADATA
apitoolkit_flask-1.0.3.dist-info/WHEEL
apitoolkit_flask-1.0.3.dist-info/top_level.txt
apitoolkit_flask-1.0.3.dist-info/RECORD
