Metadata-Version: 2.1
Name: apitoolkit-flask
Version: 1.0.3
Summary: A Flask SDK for Apitoolkit integration
Author: APIToolkit
Author-email: hello@apitoolkit.io
Requires-Dist: Flask
Requires-Dist: apitoolkit-common
Requires-Dist: opentelemetry-api>=1.0.0
